week-4/2_1_MUX/mux.v
module and1(y,a,b);
    output y;
    input a,b;

    assign y = a&b;
    
endmodule

module or1(y,a,b);
    output y;
    input a,b;

    assign y = a|b;
    
endmodule

module not1(y,a);
    output y;
    input a;

    assign y=!a;

endmodule

module mux(y,j,i0,i1);
    output y;
    input i0, i1, j;
    wire w1, w2, w3;

    and1 a1(w2,i1,j);
    not1 n1(w1,j);
    and1 a2(w3,w1,i0);
    or1 o1(y,w2,w3);

endmodule

week-4/4_1 MUX/mux_tb.v
`define TESTVECS 16

module mux_4_1;
    reg[3:0]i;
    reg s0, s1;

    wire w1, w2, y;

    reg[5:0]vec[0:15];

    mux m1(w1,s0,i[0],i[1]);
    mux m2(w2,s0,i[2],i[3]);
    mux m3(y,s1,w1,w2);

    integer j;

    initial
    begin
        for(j=0; j<`TESTVECS; j = j+1)
        begin
            #20 {s0,s1,i} = vec[j];
        end

        #20 $finish;
    end

    initial
    begin
        vec[0]  = 6'b000000;
        vec[1]  = 6'b000001;
        vec[2]  = 6'b000010;
        vec[3]  = 6'b000011;
        vec[4]  = 6'b000100;
        vec[5]  = 6'b000101;
        vec[6]  = 6'b000110;
        vec[7]  = 6'b000111;
        vec[8]  = 6'b111000;
        vec[9]  = 6'b111001;
        vec[10] = 6'b111010;
        vec[11] = 6'b111011;
        vec[12] = 6'b111100;
        vec[13] = 6'b111101;
        vec[14] = 6'b111110;
        vec[15] = 6'b111111; 
    end

    initial
    begin
        $monitor($time," s0 = %b, s1 = %b, i[3] = %b, i[2] = %b, i[1] = %b, i[0] = %b, y = %b",s0,s1,i[3],i[2],i[1],i[0],y);
    end

    initial
    begin
        $dumpfile("mux_4_1.vcd");
        $dumpvars(0,mux_4_1);
    end

endmodule

week-4/4_1 MUX/mux_4_1.vcd
$date
	Fri Aug 28 20:01:59 2026
$end
$version
	Icarus Verilog
$end
$timescale
	1s
$end
$scope module mux_4_1 $end
$var wire 1 ! w1 $end
$var wire 1 " w2 $end
$var wire 1 # y $end
$var reg 4 $ i [3:0] $end
$var integer 32 % j [31:0] $end
$var reg 1 & s0 $end
$var reg 1 ' s1 $end
$scope module m1 $end
$var wire 1 ( i0 $end
$var wire 1 ) i1 $end
$var wire 1 * j $end
$var wire 1 + w1 $end
$var wire 1 , w2 $end
$var wire 1 - w3 $end
$var wire 1 ! y $end
$scope module a1 $end
$var wire 1 ) a $end
$var wire 1 * b $end
$var wire 1 , y $end
$upscope $end
$scope module n1 $end
$var wire 1 * a $end
$var wire 1 + y $end
$upscope $end
$scope module a2 $end
$var wire 1 + a $end
$var wire 1 ( b $end
$var wire 1 - y $end
$upscope $end
$scope module o1 $end
$var wire 1 , a $end
$var wire 1 - b $end
$var wire 1 ! y $end
$upscope $end
$upscope $end
$scope module m2 $end
$var wire 1 . i0 $end
$var wire 1 / i1 $end
$var wire 1 * j $end
$var wire 1 0 w1 $end
$var wire 1 1 w2 $end
$var wire 1 2 w3 $end
$var wire 1 " y $end
$scope module a1 $end
$var wire 1 / a $end
$var wire 1 * b $end
$var wire 1 1 y $end
$upscope $end
$scope module n1 $end
$var wire 1 * a $end
$var wire 1 0 y $end
$upscope $end
$scope module a2 $end
$var wire 1 0 a $end
$var wire 1 . b $end
$var wire 1 2 y $end
$upscope $end
$scope module o1 $end
$var wire 1 1 a $end
$var wire 1 2 b $end
$var wire 1 " y $end
$upscope $end
$upscope $end
$scope module m3 $end
$var wire 1 ! i0 $end
$var wire 1 " i1 $end
$var wire 1 3 j $end
$var wire 1 4 w1 $end
$var wire 1 5 w2 $end
$var wire 1 6 w3 $end
$var wire 1 # y $end
$scope module a1 $end
$var wire 1 " a $end
$var wire 1 3 b $end
$var wire 1 5 y $end
$upscope $end
$scope module n1 $end
$var wire 1 3 a $end
$var wire 1 4 y $end
$upscope $end
$scope module a2 $end
$var wire 1 4 a $end
$var wire 1 ! b $end
$var wire 1 6 y $end
$upscope $end
$scope module o1 $end
$var wire 1 5 a $end
$var wire 1 6 b $end
$var wire 1 # y $end
$upscope $end
$upscope $end
$upscope $end
$enddefinitions $end
#0
$dumpvars
x6
x5
x4
x3
x2
x1
x0
x/
x.
x-
x,
x+
x*
x)
x(
x'
x&
b0 %
bx $
x#
x"
x!
$end
#20
0#
06
0!
0"
0,
0-
01
02
05
0(
0)
0.
0/
b1 %
0&
0*
1+
10
0'
03
14
b0 $
#40
1#
16
1!
1-
1(
b10 %
b1 $
#60
0#
06
0!
0-
0(
1)
b11 %
b10 $
#80
1#
16
1!
1-
1(
b100 %
b11 $
#100
0#
06
0!
1"
0-
12
0(
0)
1.
b101 %
b100 $
#120
1#
16
1!
1-
1(
b110 %
b101 $
#140
0#
06
0!
0-
0(
1)
b111 %
b110 $
#160
1#
16
1!
1-
1(
b1000 %
b111 $
#180
0!
0-
11
02
15
06
0(
0)
0.
1/
b1001 %
1&
1*
0+
00
1'
13
04
b1000 $
#200
1(
b1010 %
b1001 $
#220
1!
1,
0(
1)
b1011 %
b1010 $
#240
1(
b1100 %
b1011 $
#260
0!
0,
0(
0)
1.
b1101 %
b1100 $
#280
1(
b1110 %
b1101 $
#300
1!
1,
0(
1)
b1111 %
b1110 $
#320
1(
b10000 %
b1111 $
