week-2/simple_circuit1/or.v
// dataflow

module or1(y,a,b);
    output y;
    input a,b;

    assign y = a|b;
    
endmodule

week-2/NOT/not.v
// dataflow

module not1(y,a);
    output y;
    input a;
    assign y=!a;
  endmodule

week-1/and1.v
// dataflow

module and1(y,a,b);
    output y;
    input a,b;

    assign y = a&b;
    
endmodule

week-2/simple_circuit1/testbench.v
// test bench

module circuit;
    wire y,d,e;
    reg a,b,c;
    and1 x(y,a,b);
    not1 n(e,c);
    or1 o(d,y,e);

    initial
    begin
        #000 a=0;b=0;c=0;
        #100 a=0;b=0;c=1;
        #100 a=0;b=1;c=0;
        #100 a=0;b=1;c=1;
        #100 a=1;b=0;c=0;
        #100 a=1;b=0;c=1;
        #100 a=1;b=1;c=0;
        #100 a=1;b=1;c=1;
    
    end

    initial
    begin
        $monitor($time,"a = %b, b = %b, c = %b, d = %b, e = %b",a,b,c,d,e);
    end

    initial
    begin
        $dumpfile("circuit.vcd");
        $dumpvars(0,circuit);
    end

endmodule

week-2/simple_circuit1/circuit.vcd
$date
	Fri Aug 14 14:38:16 2026
$end
$version
	Icarus Verilog
$end
$timescale
	1s
$end
$scope module circuit $end
$var wire 1 ! d $end
$var wire 1 " e $end
$var wire 1 # y $end
$var reg 1 $ a $end
$var reg 1 % b $end
$var reg 1 & c $end
$scope module x $end
$var wire 1 ' a $end
$var wire 1 ( b $end
$var wire 1 # y $end
$upscope $end
$scope module n $end
$var wire 1 ) a $end
$var wire 1 " y $end
$upscope $end
$scope module o $end
$var wire 1 # a $end
$var wire 1 " b $end
$var wire 1 ! y $end
$upscope $end
$upscope $end
$enddefinitions $end
#0
$dumpvars
0)
0(
0'
0&
0%
0$
0#
1"
1!
$end
#100
0!
1&
1)
0"
#200
1!
0&
0)
1"
1%
1(
#300
0!
1&
1)
0"
#400
1!
0&
0)
1"
0%
0(
1$
1'
#500
0!
1&
1)
0"
#600
1!
1#
0&
0)
1"
1%
1(
#700
1&
1)
0"
